CHANGES
LICENSE
MANIFEST.in
README.rst
distribute_setup.py
setup.cfg
setup.py
doc/build/Makefile
doc/build/caching.rst
doc/build/conf.py
doc/build/defs.rst
doc/build/filtering.rst
doc/build/index.rst
doc/build/inheritance.rst
doc/build/namespaces.rst
doc/build/runtime.rst
doc/build/syntax.rst
doc/build/unicode.rst
doc/build/usage.rst
doc/build/builder/__init__.py
doc/build/builder/builders.py
doc/build/builder/util.py
doc/build/static/docs.css
doc/build/static/makoLogo.png
doc/build/static/site.css
doc/build/templates/base.mako
doc/build/templates/genindex.mako
doc/build/templates/layout.mako
doc/build/templates/page.mako
doc/build/templates/rtd_layout.mako
doc/build/templates/search.mako
examples/bench/basic.py
examples/bench/cheetah/footer.tmpl
examples/bench/cheetah/header.tmpl
examples/bench/cheetah/template.tmpl
examples/bench/django/templatetags/__init__.py
examples/bench/django/templatetags/bench.py
examples/bench/kid/base.kid
examples/bench/kid/template.kid
examples/bench/myghty/base.myt
examples/bench/myghty/template.myt
examples/wsgi/run_wsgi.py
hmako/__init__.py
hmako/_ast_util.py
hmako/ast.py
hmako/cache.py
hmako/codegen.py
hmako/compat.py
hmako/exceptions.py
hmako/filters.py
hmako/lexer.py
hmako/lookup.py
hmako/parsetree.py
hmako/pygen.py
hmako/pyparser.py
hmako/runtime.py
hmako/template.py
hmako/util.py
hmako.egg-info/PKG-INFO
hmako.egg-info/SOURCES.txt
hmako.egg-info/dependency_links.txt
hmako.egg-info/not-zip-safe
hmako.egg-info/top_level.txt
hmako/ext/__init__.py
hmako/ext/autohandler.py
hmako/ext/babelplugin.py
hmako/ext/beaker_cache.py
hmako/ext/preprocessors.py
hmako/ext/pygmentplugin.py
hmako/ext/turbogears.py
test/__init__.py
test/sample_module_namespace.py
test/test_ast.py
test/test_babelplugin.py
test/test_block.py
test/test_cache.py
test/test_call.py
test/test_decorators.py
test/test_def.py
test/test_exceptions.py
test/test_filters.py
test/test_inheritance.py
test/test_lexer.py
test/test_lookup.py
test/test_loop.py
test/test_lru.py
test/test_namespace.py
test/test_pygen.py
test/test_template.py
test/test_tgplugin.py
test/test_util.py
test/util.py
test/foo/__init__.py
