Metadata-Version: 1.0
Name: hmako
Version: 1.16
Summary: a hack version mako(0.74) for html , will remove empty line
Home-page: UNKNOWN
Author: zsp
Author-email: zsp007@gmail.com
License: MIT
Keywords: wsgi myghty mako
Platform: UNKNOWN
